datapizza/tools/SQLDatabase/__init__.py
datapizza/tools/SQLDatabase/base.py
datapizza_ai_tools_sqldatabase-0.0.2.dist-info/METADATA
datapizza_ai_tools_sqldatabase-0.0.2.dist-info/WHEEL
datapizza_ai_tools_sqldatabase-0.0.2.dist-info/RECORD
