Metadata-Version: 2.4
Name: datapizza-ai-tools-sqldatabase
Version: 0.0.2
Summary: A tool to interact with SQL databases for the datapizza-ai framework.
Author-email: Nilthon Jhon Rojas Apumayta <oneill.jhon97@gmail.com>
License: MIT
Classifier: License :: OSI Approved :: MIT License
Classifier: Operating System :: OS Independent
Classifier: Programming Language :: Python :: 3
Requires-Python: <4,>=3.10.0
Requires-Dist: datapizza-ai-core<0.1.0,>=0.0.1
Requires-Dist: sqlalchemy>=2.0.44
